devai.py
devai_runner.py
agent/__init__.py
agent/agent.py
agent/events.py
agent/persistence.py
agent/session.py
client/__init__.py
client/llm_client.py
client/manual_llm.py
client/response.py
config/__init__.py
config/config.py
config/loader.py
context/__init__.py
context/compaction.py
context/loop_detector.py
context/manager.py
devai_agent-2.0.5.dist-info/licenses/LICENSE
hooks/__init__.py
hooks/hook_system.py
prompts/__init__.py
prompts/system.py
safety/__init__.py
safety/approval.py
tools/__init__.py
tools/base.py
tools/discovery.py
tools/registry.py
tools/subagents.py
tools/builtin/__init__.py
tools/builtin/edit_file.py
tools/builtin/glob.py
tools/builtin/grep.py
tools/builtin/lint.py
tools/builtin/list_dir.py
tools/builtin/memory.py
tools/builtin/read_file.py
tools/builtin/shell.py
tools/builtin/todo.py
tools/builtin/web_fetch.py
tools/builtin/web_search.py
tools/builtin/write_file.py
tools/mcp/__init__.py
tools/mcp/client.py
tools/mcp/mcp_manager.py
tools/mcp/mcp_tool.py
ui/__init__.py
ui/tui.py
utils/__init__.py
utils/errors.py
utils/paths.py
utils/text.py
devai_agent-2.0.5.dist-info/METADATA
devai_agent-2.0.5.dist-info/WHEEL
devai_agent-2.0.5.dist-info/entry_points.txt
devai_agent-2.0.5.dist-info/top_level.txt
devai_agent-2.0.5.dist-info/RECORD
